idun_agent_engine/__init__.py
idun_agent_engine/_version.py
idun_agent_engine/py.typed
idun_agent_engine/agent/__init__.py
idun_agent_engine/agent/base.py
idun_agent_engine/agent/adk/__init__.py
idun_agent_engine/agent/adk/adk.py
idun_agent_engine/agent/haystack/__init__.py
idun_agent_engine/agent/haystack/haystack.py
idun_agent_engine/agent/haystack/haystack_model.py
idun_agent_engine/agent/haystack/utils.py
idun_agent_engine/agent/langgraph/__init__.py
idun_agent_engine/agent/langgraph/langgraph.py
idun_agent_engine/core/__init__.py
idun_agent_engine/core/app_factory.py
idun_agent_engine/core/config_builder.py
idun_agent_engine/core/engine_config.py
idun_agent_engine/core/server_runner.py
idun_agent_engine/guardrails/__init__.py
idun_agent_engine/guardrails/base.py
idun_agent_engine/guardrails/guardrails_hub/__init__.py
idun_agent_engine/guardrails/guardrails_hub/guardrails_hub.py
idun_agent_engine/guardrails/guardrails_hub/utils.py
idun_agent_engine/mcp/__init__.py
idun_agent_engine/mcp/helpers.py
idun_agent_engine/mcp/registry.py
idun_agent_engine/observability/__init__.py
idun_agent_engine/observability/base.py
idun_agent_engine/observability/gcp_logging/__init__.py
idun_agent_engine/observability/gcp_logging/gcp_logging_handler.py
idun_agent_engine/observability/gcp_trace/__init__.py
idun_agent_engine/observability/gcp_trace/gcp_trace_handler.py
idun_agent_engine/observability/langfuse/__init__.py
idun_agent_engine/observability/langfuse/langfuse_handler.py
idun_agent_engine/observability/phoenix/__init__.py
idun_agent_engine/observability/phoenix/phoenix_handler.py
idun_agent_engine/observability/phoenix_local/__init__.py
idun_agent_engine/observability/phoenix_local/phoenix_local_handler.py
idun_agent_engine/server/__init__.py
idun_agent_engine/server/dependencies.py
idun_agent_engine/server/lifespan.py
idun_agent_engine/server/server_config.py
idun_agent_engine/server/routers/__init__.py
idun_agent_engine/server/routers/agent.py
idun_agent_engine-0.4.1.dist-info/METADATA
idun_agent_engine-0.4.1.dist-info/WHEEL
idun_agent_engine-0.4.1.dist-info/entry_points.txt
idun_agent_engine-0.4.1.dist-info/RECORD
