Metadata-Version: 2.4
Name: idun-agent-engine
Version: 0.4.1
Summary: Python SDK and runtime to serve AI agents with FastAPI, LangGraph, and observability.
Project-URL: Homepage, https://github.com/geoffreyharrazi/idun-agent-platform
Project-URL: Repository, https://github.com/geoffreyharrazi/idun-agent-platform
Project-URL: Documentation, https://github.com/geoffreyharrazi/idun-agent-platform/tree/main/libs/idun_agent_engine
Project-URL: Issues, https://github.com/geoffreyharrazi/idun-agent-platform/issues
Author-email: Geoffrey HARRAZI <geoffreyharrazi@gmail.com>
License-Expression: GPL-3.0-only
Keywords: agents,fastapi,langgraph,llm,observability,sdk
Classifier: Framework :: FastAPI
Classifier: Intended Audience :: Developers
Classifier: License :: OSI Approved :: GNU General Public License v3 (GPLv3)
Classifier: Programming Language :: Python :: 3
Classifier: Programming Language :: Python :: 3 :: Only
Classifier: Programming Language :: Python :: 3.12
Classifier: Programming Language :: Python :: 3.13
Classifier: Topic :: Software Development :: Libraries
Classifier: Typing :: Typed
Requires-Python: <3.14,>=3.12
Requires-Dist: ag-ui-adk<0.4.0,>=0.3.4
Requires-Dist: ag-ui-langgraph<0.1.0,>=0.0.20
Requires-Dist: ag-ui-protocol<0.2.0,>=0.1.8
Requires-Dist: aiosqlite<0.22.0,>=0.21.0
Requires-Dist: arize-phoenix-otel<1.0.0,>=0.2.0
Requires-Dist: arize-phoenix<12.0.0,>=11.22.0
Requires-Dist: click>=8.2.0
Requires-Dist: copilotkit<0.2.0,>=0.1.72
Requires-Dist: deepagents<1.0.0,>=0.2.8
Requires-Dist: fastapi<0.116.0,>=0.115.0
Requires-Dist: google-adk<2.0.0,>=1.19.0
Requires-Dist: google-cloud-logging<4.0.0,>=3.10.0
Requires-Dist: guardrails-ai<0.8.0,>=0.7.2
Requires-Dist: httpx<0.29.0,>=0.28.1
Requires-Dist: idun-agent-schema<1.0.0,>=0.3.8
Requires-Dist: langchain-core<2.0.0,>=1.0.0
Requires-Dist: langchain-google-vertexai<4.0.0,>=2.0.27
Requires-Dist: langchain-mcp-adapters<0.3.0,>=0.2.0
Requires-Dist: langchain<2.0.0,>=1.0.0
Requires-Dist: langfuse-haystack>=2.3.0
Requires-Dist: langfuse<4.0.0,>=2.60.8
Requires-Dist: langgraph-checkpoint-postgres<4.0.0,>=3.0.0
Requires-Dist: langgraph-checkpoint-sqlite<4.0.0,>=3.0.0
Requires-Dist: langgraph<2.0.0,>=1.0.0
Requires-Dist: mcp<2.0.0,>=1.0.0
Requires-Dist: openinference-instrumentation-google-adk<1.0.0,>=0.1.0
Requires-Dist: openinference-instrumentation-guardrails<1.0.0,>=0.1.0
Requires-Dist: openinference-instrumentation-langchain<1.0.0,>=0.1.13
Requires-Dist: openinference-instrumentation-mcp<2.0.0,>=1.0.0
Requires-Dist: openinference-instrumentation-vertexai<1.0.0,>=0.1.0
Requires-Dist: opentelemetry-exporter-gcp-trace<2.0.0,>=1.6.0
Requires-Dist: opentelemetry-exporter-otlp-proto-http<2.0.0,>=1.22.0
Requires-Dist: platformdirs<5.0.0,>=4.0.0
Requires-Dist: posthog<8.0.0,>=7.0.0
Requires-Dist: psycopg-binary<4.0.0,>=3.3.0
Requires-Dist: pydantic<3.0.0,>=2.11.7
Requires-Dist: python-dotenv>=1.1.1
Requires-Dist: pyyaml<7.0.0,>=6.0.0
Requires-Dist: sqlalchemy<3.0.0,>=2.0.36
Requires-Dist: streamlit<2.0.0,>=1.47.1
Requires-Dist: tavily-python<0.8.0,>=0.7.9
Requires-Dist: textual<7.4.0,>=7.3.0
Requires-Dist: uvicorn<0.36.0,>=0.35.0
